{
  "_fv": 43,
  "_type": "tool",
  "definition": {
    "renderType": 0,
    "texture": "alteraxe",
    "customModelName": "Normal",
    "name": "Alter Axe",
    "specialInfo": [
      "Looks..."
    ],
    "creativeTab": {
      "value": "CUSTOM:REM"
    },
    "toolType": "Axe",
    "harvestLevel": 4,
    "efficiency": 9.0,
    "attackSpeed": 1.0,
    "enchantability": 13,
    "damageVsEntity": 9.0,
    "usageCount": 1500,
    "blocksAffected": [],
    "hasGlow": false,
    "repairItems": [
      {
        "value": "CUSTOM:AlterDiamond"
      },
      {
        "value": "Items.AMETHYST_SHARD"
      }
    ],
    "immuneToFire": false,
    "stayInGridWhenCrafting": false,
    "damageOnCrafting": false
  }
}